collective/__init__.py
collective/techevent/__init__.py
collective/techevent/_types.py
collective/techevent/configure.zcml
collective/techevent/dependencies.zcml
collective/techevent/interfaces.py
collective/techevent/permissions.zcml
collective/techevent/profiles.zcml
collective/techevent/testing.py
collective/techevent/behaviors/__init__.py
collective/techevent/behaviors/configure.zcml
collective/techevent/behaviors/presenter.py
collective/techevent/behaviors/schedule.py
collective/techevent/behaviors/session.py
collective/techevent/behaviors/tech_event.py
collective/techevent/content/__init__.py
collective/techevent/content/presenter.py
collective/techevent/content/tech_event.py
collective/techevent/content/location/__init__.py
collective/techevent/content/location/room.py
collective/techevent/content/location/venue.py
collective/techevent/content/schedule/__init__.py
collective/techevent/content/schedule/keynote.py
collective/techevent/content/schedule/lightning_talks.py
collective/techevent/content/schedule/openspace.py
collective/techevent/content/schedule/schedule.py
collective/techevent/content/schedule/session.py
collective/techevent/content/schedule/slot.py
collective/techevent/content/schedule/talk.py
collective/techevent/content/schedule/training.py
collective/techevent/content/schedule/slots/__init__.py
collective/techevent/content/schedule/slots/meeting.py
collective/techevent/content/schedule/slots/schedule_break.py
collective/techevent/content/sponsors/__init__py
collective/techevent/content/sponsors/sponsor.py
collective/techevent/content/sponsors/sponsor_level.py
collective/techevent/content/sponsors/sponsors_db.py
collective/techevent/controlpanel/__init__.py
collective/techevent/controlpanel/configure.zcml
collective/techevent/controlpanel/tech_event.py
collective/techevent/deserializers/__init__.py
collective/techevent/deserializers/configure.zcml
collective/techevent/deserializers/datagrid.py
collective/techevent/fields/__init__.py
collective_techevent-1.0.0a23.dist-info/METADATA
collective_techevent-1.0.0a23.dist-info/WHEEL
collective_techevent-1.0.0a23.dist-info/entry_points.txt
collective_techevent-1.0.0a23.dist-info/licenses/LICENSE.GPL
collective_techevent-1.0.0a23.dist-info/licenses/LICENSE.md
collective_techevent-1.0.0a23.dist-info/RECORD
