Metadata-Version: 2.4
Name: collective.techevent
Version: 1.0.0a23
Summary: Support for implementing tech conference in a Plone site.
Project-URL: Homepage, https://github.com/collective/tech-event
Project-URL: PyPI, https://pypi.org/project/collective.techevent
Project-URL: Source, https://github.com/collective/tech-event
Project-URL: Tracker, https://github.com/collective/tech-event/issues
Author-email: PloneGov-BR <gov@plone.org.br>
License-Expression: GPL-2.0-only
License-File: LICENSE.GPL
License-File: LICENSE.md
Keywords: CMS,Plone,Python
Classifier: Development Status :: 3 - Alpha
Classifier: Environment :: Web Environment
Classifier: Framework :: Plone
Classifier: Framework :: Plone :: 6.0
Classifier: Framework :: Plone :: 6.1
Classifier: Framework :: Plone :: Addon
Classifier: Operating System :: OS Independent
Classifier: Programming Language :: Python
Classifier: Programming Language :: Python :: 3.10
Classifier: Programming Language :: Python :: 3.11
Classifier: Programming Language :: Python :: 3.12
Classifier: Programming Language :: Python :: 3.13
Requires-Python: >=3.10
Requires-Dist: collective-z3cform-datagridfield
Requires-Dist: plone-api
Requires-Dist: plone-restapi>=9.15.2
Requires-Dist: plone-volto
Requires-Dist: plonegovbr-socialmedia
Requires-Dist: products-cmfplone
Provides-Extra: test
Requires-Dist: horse-with-no-namespace; extra == 'test'
Requires-Dist: plone-app-testing; extra == 'test'
Requires-Dist: plone-restapi[test]; extra == 'test'
Requires-Dist: products-printingmailhost; extra == 'test'
Requires-Dist: pytest-cov; extra == 'test'
Requires-Dist: pytest-plone>=1.0.0a2; extra == 'test'
Requires-Dist: pytest>=8.0.0; extra == 'test'
Provides-Extra: users
Requires-Dist: products-membrane; extra == 'users'
Requires-Dist: pyotp; extra == 'users'
